mips_pipe.v
module pipe_MIPS32 (clk1,clk2);
     input clk1,clk2;//two-phase clock
//defining sub-stage variables at different stages
reg [31:0] PC,IF_ID_IR,IF_ID_NPC;
reg [31:0] ID_EX_IR,ID_EX_NPC,ID_EX_A,ID_EX_B,ID_EX_Imm;
reg [2:0] ID_EX_type,EX_MEM_type,MEM_WB_type;
reg [31:0] EX_MEM_IR,EX_MEM_ALUout,EX_MEM_B;
reg        EX_MEM_cond;
reg [31:0] MEM_WB_IR,MEM_WB_ALUout,MEM_WB_LMD;

reg [31:0] Reg [0:31];//register bank (32x32)
reg [31:0] Mem [0:1023];//1025x32 memory

parameter ADD=6'b000000, SUB=6'b000001, AND=6'b000010, OR=6'b000011, SLT=6'b000100, MUL=6'b000101,HLT=6'b111111,LW=6'b001000,SW=6'b001001,ADDI=6'b001010,SUBI=6'b001011,SLTI=6'b001100,BNEQZ=6'b001101,BEQZ=6'b001110;
parameter RR_ALU=3'b000, RM_ALU=3'b001, LOAD=3'b010, STORE=3'b011, BRANCH=3'b100, HALT=3'b101;


reg HALTED;
//Set after HLT instruction is completed(in WB stage)
reg TAKEN_BRANCH;
//Required to disable instructions after branch

//IF Stage
always @(posedge clk1)                                  // IF Stage
if (HALTED == 0)
begin
  if (((EX_MEM_IR[31:26] == BEQZ) && (EX_MEM_cond == 1)) || ((EX_MEM_IR[31:26] == BNEQZ) && (EX_MEM_cond == 0)))
     begin
          IF_ID_IR      <= #2 Mem[EX_MEM_ALUout];
          TAKEN_BRANCH  <= #2 1'b1;
          IF_ID_NPC     <= #2 EX_MEM_ALUout + 1;
          PC            <= #2 EX_MEM_ALUout + 1;
     end
  else
     begin
          IF_ID_IR      <= #2 Mem[PC];
          IF_ID_NPC     <= #2 PC + 1;
          PC            <= #2 PC + 1;
     end
end
//ID Stage 
always @(posedge clk2)                                  // ID Stage
if (HALTED == 0)
begin
          if (IF_ID_IR[25:21] == 5'b00000)  
               ID_EX_A   <= 0;
          else 
               ID_EX_A   <= #2 Reg[IF_ID_IR[25:21]]; // "rs"

          if (IF_ID_IR[20:16] == 5'b00000)  
               ID_EX_B   <= 0;
          else 
               ID_EX_B   <= #2 Reg[IF_ID_IR[20:16]]; // "rt"

          ID_EX_NPC      <= #2 IF_ID_NPC;
          ID_EX_IR       <= #2 IF_ID_IR;
          ID_EX_Imm      <= #2 {{16{IF_ID_IR[15]}}, {IF_ID_IR[15:0]}};
     

     case (IF_ID_IR[31:26])
          ADD,SUB,AND,OR,SLT,MUL: ID_EX_type <= #2 RR_ALU;
          ADDI,SUBI,SLTI:         ID_EX_type <= #2 RM_ALU;
          LW:                     ID_EX_type <= #2 LOAD;
          SW:                     ID_EX_type <= #2 STORE;
          BNEQZ,BEQZ:             ID_EX_type <= #2 BRANCH;
          HLT:                    ID_EX_type <= #2 HALT;
          default:                ID_EX_type <= #2 HALT;// Invalid opcode
     endcase
end


always @(posedge clk1)// EX Stage
if (HALTED == 0)
begin
  EX_MEM_type   <= #2 ID_EX_type;
  EX_MEM_IR     <= #2 ID_EX_IR;
  TAKEN_BRANCH  <= #2 0;

  case (ID_EX_type)
     RR_ALU: 
     begin
          case (ID_EX_IR[31:26])// "opcode"
               ADD:    EX_MEM_ALUout <= #2 ID_EX_A + ID_EX_B;
               SUB:    EX_MEM_ALUout <= #2 ID_EX_A - ID_EX_B;
               AND:    EX_MEM_ALUout <= #2 ID_EX_A & ID_EX_B;
               OR:     EX_MEM_ALUout <= #2 ID_EX_A | ID_EX_B;
               SLT:    EX_MEM_ALUout <= #2 ID_EX_A < ID_EX_B;
               MUL:    EX_MEM_ALUout <= #2 ID_EX_A * ID_EX_B;
               default: EX_MEM_ALUout <= #2 32'hxxxxxxxx;
          endcase
    end
     RM_ALU: 
     begin
          case (ID_EX_IR[31:26])// "opcode"
               ADDI:    EX_MEM_ALUout <= #2 ID_EX_A + ID_EX_Imm;
               SUBI:    EX_MEM_ALUout <= #2 ID_EX_A - ID_EX_Imm;
               SLTI:    EX_MEM_ALUout <= #2 ID_EX_A < ID_EX_Imm;
               default: EX_MEM_ALUout <= #2 32'hxxxxxxxx;
          endcase
     end

     LOAD, STORE:
     begin
          EX_MEM_ALUout <= #2 ID_EX_A + ID_EX_Imm;
          EX_MEM_B      <= #2 ID_EX_B;
     end

     BRANCH: 
     begin
          EX_MEM_ALUout <= #2 ID_EX_NPC + ID_EX_Imm;
          EX_MEM_cond   <= #2 (ID_EX_A == 0);
     end

endcase
end
   
always @(posedge clk2)// MEM Stage
if (HALTED == 0)
begin
  MEM_WB_type       <= #2 EX_MEM_type;
  MEM_WB_IR         <= #2 EX_MEM_IR;

  case (EX_MEM_type)
     RR_ALU, RM_ALU:
          MEM_WB_ALUout       <= #2 EX_MEM_ALUout;

     LOAD:
          MEM_WB_LMD          <= #2 Mem[EX_MEM_ALUout];

     STORE:
      if (TAKEN_BRANCH == 0)// Disable write
        Mem[EX_MEM_ALUout]    <= #2 EX_MEM_B;

  endcase
end


always @(posedge clk1)// WB Stage
begin
  if (TAKEN_BRANCH == 0)// Disable write if branch taken
    case (MEM_WB_type)
      RR_ALU:   
          Reg[MEM_WB_IR[15:11]]    <= #2 MEM_WB_ALUout;// "rd"
      RM_ALU:   
          Reg[MEM_WB_IR[20:16]]    <= #2 MEM_WB_ALUout;// "rt"
      LOAD:     
          Reg[MEM_WB_IR[20:16]]    <= #2 MEM_WB_LMD;// "rt"
      HALT:     
          HALTED <= #2 1'b1;
    endcase
end

endmodule

mips_pipe_tb2.v
module test_mips32;

    reg clk1,clk2;
    integer k;

    pipe_MIPS32 mips (clk1,clk2);

    initial
        begin
            clk1 = 0; clk2 = 0;
            repeat(50) //Generating two-phase clock
            begin
                #5 clk1 = 1; #5 clk1 =0;
                #5 clk2 = 1; #5 clk2 =0;
            end
        end
    initial // Initialization and test vectors
        begin
            for(k=0;k<31;k++)
                mips.Reg[k] = k;

            mips.Mem[0] = 32'h28010078; //ADDI R1,R0,120
            mips.Mem[1] = 32'h0c631800; //OR R3,R3,R3 -- dummy instruction
            mips.Mem[2] = 32'h20220000; //LW R2,0(R1)
            mips.Mem[3] = 32'h0c631800; //OR R3,R3,R3 -- dummy instruction
            mips.Mem[4] = 32'h2842002d; //ADDI R2,R2,45
            mips.Mem[5] = 32'h0c631800; //OR R3,R3,R3 -- dummy instruction
            mips.Mem[6] = 32'h24220001; //SW R2,1(R1)
            mips.Mem[7] = 32'hfc000000; //HLT
            
            mips.Mem[120] = 85;         // <--- Semicolon fixed on previous line (now correct)

            mips.PC = 0;                // <--- Moved inside the block
            mips.HALTED = 0;            // <--- Moved inside the block
            mips.TAKEN_BRANCH = 0;      // <--- Moved inside the block

            #500 $display("Mem[120]: %4d \nMem[121]: %4d",mips.Mem[120],mips.Mem[121]);
        end // <--- Closing 'end' for the initial block
        initial
            begin 
                $dumpfile("mips2.vcd");
                $dumpvars(0,test_mips32);
                #600 $finish;
            end
endmodule

mips.vcd
$date
	Sat Oct 18 05:37:04 2025
$end
$version
	Icarus Verilog
$end
$timescale
	1s
$end
$scope module test_mips32 $end
$var reg 1 ! clk1 $end
$var reg 1 " clk2 $end
$var integer 32 # k [31:0] $end
$scope module mips $end
$var wire 1 ! clk1 $end
$var wire 1 " clk2 $end
$var reg 32 $ EX_MEM_ALUout [31:0] $end
$var reg 32 % EX_MEM_B [31:0] $end
$var reg 32 & EX_MEM_IR [31:0] $end
$var reg 1 ' EX_MEM_cond $end
$var reg 3 ( EX_MEM_type [2:0] $end
$var reg 1 ) HALTED $end
$var reg 32 * ID_EX_A [31:0] $end
$var reg 32 + ID_EX_B [31:0] $end
$var reg 32 , ID_EX_IR [31:0] $end
$var reg 32 - ID_EX_Imm [31:0] $end
$var reg 32 . ID_EX_NPC [31:0] $end
$var reg 3 / ID_EX_type [2:0] $end
$var reg 32 0 IF_ID_IR [31:0] $end
$var reg 32 1 IF_ID_NPC [31:0] $end
$var reg 32 2 MEM_WB_ALUout [31:0] $end
$var reg 32 3 MEM_WB_IR [31:0] $end
$var reg 32 4 MEM_WB_LMD [31:0] $end
$var reg 3 5 MEM_WB_type [2:0] $end
$var reg 32 6 PC [31:0] $end
$var reg 1 7 TAKEN_BRANCH $end
$upscope $end
$upscope $end
$enddefinitions $end
#0
$dumpvars
07
b0 6
bx 5
bx 4
bx 3
bx 2
bx 1
bx 0
bx /
bx .
bx -
bx ,
bx +
bx *
0)
bx (
x'
bx &
bx %
bx $
b11111 #
0"
0!
$end
#5
1!
#7
b1 6
b1 1
b101000000000010000000000001010 0
#10
0!
#15
b0 *
1"
#17
b1 /
b1010 -
b101000000000010000000000001010 ,
b1 .
b1 +
#20
0"
#25
1!
#27
b1010 $
b101000000000010000000000001010 &
b1 (
b10 6
b10 1
b101000000000100000000000010100 0
#30
0!
#35
1"
#37
b1010 2
b101000000000010000000000001010 3
b1 5
b10100 -
b101000000000100000000000010100 ,
b10 .
b10 +
#40
0"
#45
1!
#47
b11 6
b11 1
b101000000000110000000000011001 0
b10100 $
b101000000000100000000000010100 &
#50
0!
#55
1"
#57
b11001 -
b101000000000110000000000011001 ,
b11 .
b11 +
b10100 2
b101000000000100000000000010100 3
#60
0"
#65
1!
#67
b11001 $
b101000000000110000000000011001 &
b100 6
b100 1
b1100111001110111100000000000 0
#70
0!
#75
1"
#77
b11001 2
b101000000000110000000000011001 3
b0 /
b111100000000000 -
b1100111001110111100000000000 ,
b100 .
b111 +
b111 *
#80
0"
#85
1!
#87
b101 6
b101 1
b111 $
b1100111001110111100000000000 &
b0 (
#90
0!
#95
1"
#97
b101 .
b111 2
b1100111001110111100000000000 3
b0 5
#100
0"
#105
1!
#107
b110 6
b110 1
b1000100010000000000000 0
#110
0!
#115
1"
#117
b10000000000000 -
b1000100010000000000000 ,
b110 .
b10100 +
b1010 *
#120
0"
#125
1!
#127
b111 6
b111 1
b1100111001110111100000000000 0
b11110 $
b1000100010000000000000 &
#130
0!
#135
1"
#137
b111100000000000 -
b1100111001110111100000000000 ,
b111 .
b111 +
b111 *
b11110 2
b1000100010000000000000 3
#140
0"
#145
1!
#147
b111 $
b1100111001110111100000000000 &
b1000 6
b1000 1
b100000110010100000000000 0
#150
0!
#155
1"
#157
b111 2
b1100111001110111100000000000 3
b10100000000000 -
b100000110010100000000000 ,
b1000 .
b11001 +
b11110 *
#160
0"
#165
1!
#167
b1001 6
b1001 1
b11111100000000000000000000000000 0
b110111 $
b100000110010100000000000 &
#170
0!
#175
b0 +
b0 *
1"
#177
b101 /
b0 -
b11111100000000000000000000000000 ,
b1001 .
b110111 2
b100000110010100000000000 3
#180
0"
#185
1!
#187
b11111100000000000000000000000000 &
b101 (
b1010 6
b1010 1
bx 0
#190
0!
#195
1"
#197
b11111100000000000000000000000000 3
b101 5
bx -
bx ,
b1010 .
bx +
bx *
#200
0"
#205
1!
#207
b1011 6
b1011 1
bx &
1)
#210
0!
#215
1"
#220
0"
#225
1!
#230
0!
#235
1"
#240
0"
#245
1!
#250
0!
#255
1"
#260
0"
#265
1!
#270
0!
#275
1"
#280
0"
b110 #
